{
  "texture": "assets/stargate/universe/default/universe_stargate.png",
  "engaged_texture": "assets/stargate/universe/default/universe_stargate_engaged.png",
  "symbols": {
    "symbol_color": {
      "red": 0.082,
      "green": 0.035,
      "blue": 0.0,
      "alpha": 1.0
    },
    "encoded_symbol_color": {
      "red": 0.784,
      "green": 0.8627,
      "blue": 1.0,
      "alpha": 1.0
    },
    "engaged_symbol_color": {
      "red": 0.784,
      "green": 0.8627,
      "blue": 1.0,
      "alpha": 1.0
    },
    "symbols_glow": false,
    "encoded_symbols_glow": true,
    "engaged_symbols_glow": true,
    "engage_encoded_symbols": true,
    "engage_symbols_on_incoming": false,
    "permanent_symbols": "universal",
    "permanent_point_of_origin": "assets/symbols/universal/universal_0_origin.png"
  }
}